LICENSE
README.md
setup.py
landsat2geojson/__init__.py
landsat2geojson/constants.py
landsat2geojson/download_band.py
landsat2geojson/feature_utils.py
landsat2geojson/main.py
landsat2geojson/overpass_search.py
landsat2geojson/process_landsat.py
landsat2geojson/search_metadata.py
landsat2geojson.egg-info/PKG-INFO
landsat2geojson.egg-info/SOURCES.txt
landsat2geojson.egg-info/dependency_links.txt
landsat2geojson.egg-info/entry_points.txt
landsat2geojson.egg-info/requires.txt
landsat2geojson.egg-info/top_level.txt