Metadata-Version: 2.1
Name: landsat2geojson
Version: 0.0.3
Summary: Script to extract features from landsat
Home-page: https://github.com/yunica/landsat2geojson
Author: Junior Flores
Author-email: junior@developmentseed.org
Keywords: earth observation,remote sesing,GIS,satellite imagery,landsat,water,usgs,geojson,overpass
Classifier: Intended Audience :: Developers
Classifier: Intended Audience :: Education
Classifier: Intended Audience :: Science/Research
Classifier: Operating System :: MacOS
Classifier: Operating System :: Microsoft :: Windows
Classifier: Operating System :: Unix
Classifier: Programming Language :: Python
Classifier: Programming Language :: Python :: 3
Classifier: Programming Language :: Python :: 3.9
Classifier: Programming Language :: Python :: 3.10
Classifier: Programming Language :: Python :: 3.11
Classifier: Topic :: Scientific/Engineering
Classifier: Topic :: Software Development
Requires-Python: >=3.9
License-File: LICENSE
